{
  "type": "FeatureCollection",
  "features": [
    {
      "type": "Feature",
      "properties": {
        "marker-color": "#7e7e7e",
        "marker-size": "medium",
        "title": "test1",
        "description": "",
        "location": "one"
      },
      "geometry": {
        "type": "Point",
        "coordinates": [
          127.03499794006346,
          37.528310786243416
        ]
      }
    },
    {
      "type": "Feature",
      "properties": {
        "title": "test2",
        "marker-color": "#7e7e7e",
        "marker-size": "medium",
        "description": "",
        "location": "two"
      },
      "geometry": {
        "type": "Point",
        "coordinates": [
          127.03315258026122,
          37.517691385443065
        ]
      }
    },
    {
      "type": "Feature",
      "properties": {
        "marker-color": "#7e7e7e",
        "title": "test3",
        "marker-size": "medium",
        "description": "",
        "location": "three"
      },
      "geometry": {
        "type": "Point",
        "coordinates": [
          127.02208042144777,
          37.52354585745457
        ]
      }
    },
    {
      "type": "Feature",
      "properties": {
        "marker-color": "#7e7e7e",
        "marker-size": "medium",
        "title": "test4",
        "description": "",
        "location": "four"
      },
      "geometry": {
        "type": "Point",
        "coordinates": [
          127.01581478118896,
          37.53059103733898
        ]
      }
    }
  ]
}
